setup.py
hpms_vdf/__init__.py
hpms_vdf/hpms_vdf.py
hpms_vdf.egg-info/PKG-INFO
hpms_vdf.egg-info/SOURCES.txt
hpms_vdf.egg-info/dependency_links.txt
hpms_vdf.egg-info/not-zip-safe
hpms_vdf.egg-info/top_level.txt