Metadata-Version: 1.0
Name: hpms-vdf
Version: 0.2
Summary: Transforms Validation Exports from HPMS 8.0 to Pandas DataFrame
Home-page: UNKNOWN
Author: Erik Mason
Author-email: ejmdpg@gmail.com
License: UNKNOWN
Platform: UNKNOWN
